llm_tests/__init__.py
llm_tests/test_files/simple_memory.json
llm_tests-0.0.3.dist-info/METADATA
llm_tests-0.0.3.dist-info/WHEEL
llm_tests-0.0.3.dist-info/licenses/LICENCE
llm_tests-0.0.3.dist-info/RECORD
