Metadata-Version: 2.4
Name: llm-tests
Version: 0.0.3
Summary: LLM Tests
Project-URL: Homepage, https://github.com/mr-randall/llm-tests
Project-URL: Issues, https://github.com/mr-randall/llm-tests/issues
Project-URL: Source, https://github.com/mr-randall/llm-tests
Author: Chris Randall
License-Expression: GPL-3.0-or-later
License-File: LICENCE
Classifier: Operating System :: OS Independent
Classifier: Programming Language :: Python :: 3
Requires-Python: >=3.9
